NiukeYingjianGongchengshiQiuzhiJingyanFenxiang20212022Fix1/README.md
NiukeYingjianGongchengshiQiuzhiJingyanFenxiang20212022Fix1/__init__.py
NiukeYingjianGongchengshiQiuzhiJingyanFenxiang20212022Fix1/__main__.py
NiukeYingjianGongchengshiQiuzhiJingyanFenxiang20212022Fix1/file.epub
NiukeYingjianGongchengshiQiuzhiJingyanFenxiang20212022Fix1/index.html
NiukeYingjianGongchengshiQiuzhiJingyanFenxiang20212022Fix1/css/__init__.py
NiukeYingjianGongchengshiQiuzhiJingyanFenxiang20212022Fix1/css/annotations.css
NiukeYingjianGongchengshiQiuzhiJingyanFenxiang20212022Fix1/css/main.css
NiukeYingjianGongchengshiQiuzhiJingyanFenxiang20212022Fix1/css/normalize.css
NiukeYingjianGongchengshiQiuzhiJingyanFenxiang20212022Fix1/css/popup.css
NiukeYingjianGongchengshiQiuzhiJingyanFenxiang20212022Fix1/font/__init__.py
NiukeYingjianGongchengshiQiuzhiJingyanFenxiang20212022Fix1/font/fontello.eot
NiukeYingjianGongchengshiQiuzhiJingyanFenxiang20212022Fix1/font/fontello.svg
NiukeYingjianGongchengshiQiuzhiJingyanFenxiang20212022Fix1/font/fontello.ttf
NiukeYingjianGongchengshiQiuzhiJingyanFenxiang20212022Fix1/font/fontello.woff
NiukeYingjianGongchengshiQiuzhiJingyanFenxiang20212022Fix1/img/__init__.py
NiukeYingjianGongchengshiQiuzhiJingyanFenxiang20212022Fix1/img/annotator-glyph-sprite.png
NiukeYingjianGongchengshiQiuzhiJingyanFenxiang20212022Fix1/img/annotator-icon-sprite.png
NiukeYingjianGongchengshiQiuzhiJingyanFenxiang20212022Fix1/img/apple-touch-icon.png
NiukeYingjianGongchengshiQiuzhiJingyanFenxiang20212022Fix1/img/cancelfullscreen.png
NiukeYingjianGongchengshiQiuzhiJingyanFenxiang20212022Fix1/img/close.png
NiukeYingjianGongchengshiQiuzhiJingyanFenxiang20212022Fix1/img/fullscreen.png
NiukeYingjianGongchengshiQiuzhiJingyanFenxiang20212022Fix1/img/loader.gif
NiukeYingjianGongchengshiQiuzhiJingyanFenxiang20212022Fix1/img/menu-icon.png
NiukeYingjianGongchengshiQiuzhiJingyanFenxiang20212022Fix1/img/save.png
NiukeYingjianGongchengshiQiuzhiJingyanFenxiang20212022Fix1/img/saved.png
niuke_yingjian_gongchengshi_qiuzhi_jingyan_fenxiang_2021_2022_fix1-2025.3.25.1.dist-info/METADATA
niuke_yingjian_gongchengshi_qiuzhi_jingyan_fenxiang_2021_2022_fix1-2025.3.25.1.dist-info/WHEEL
niuke_yingjian_gongchengshi_qiuzhi_jingyan_fenxiang_2021_2022_fix1-2025.3.25.1.dist-info/entry_points.txt
niuke_yingjian_gongchengshi_qiuzhi_jingyan_fenxiang_2021_2022_fix1-2025.3.25.1.dist-info/top_level.txt
niuke_yingjian_gongchengshi_qiuzhi_jingyan_fenxiang_2021_2022_fix1-2025.3.25.1.dist-info/RECORD
